Workbook

Sheet Acuerdo
B2: ACUERDO COMERCIAL — VENDEDOR DocFácil
B4: 1. Esquema de comisión
B5: • La comisión por cada nueva clínica vendida es de 1.5× la primera mensualidad del plan contratado.
B6: • Ejemplo: plan Pro $299/mes → comisión total $448.50 por venta.
B7: • Aplica a todos los planes de pago: Básico, Pro y Clínica. El plan Free NO paga comisión.
B9: 2. Pago en dos exhibiciones (split 50/50)
B10: • 50% (primera mitad) se paga cuando la clínica realiza su PRIMER pago real al sistema.
B11: • 50% (segunda mitad) se paga cuando la clínica realiza su SEGUNDO pago mensual.
B12: • Ejemplo Pro: $224.25 al 1er pago + $224.25 al 2do pago = $448.50 total.
B13: • Si la clínica NO hace el 2do pago, la segunda mitad no se paga.
B15: 3. Clawback (devolución de comisión)
B16: • Si la clínica cancela antes de 90 días desde la fecha de venta, las comisiones quedan en estado "clawback".
... B44: Firma DocFácil: _____________________________ Fecha: _______________

Sheet Calculadora
A1: CALCULADORA DE INGRESOS — Juega con los números
A3: CAMBIA ESTOS VALORES PARA VER TUS INGRESOS:
A4: Plan a vender | B4: Profesional | D4: Precio mensual | E4: =IFERROR(VLOOKUP(B4,Planes!A4:B7,2,FALSE),0) -> 0
A5: Ventas por mes (esperadas) | B5: 10 | D5: Comisión total por venta (1.5×) | E5: =IF(B4="Free",0,E4*1.5) -> 0
A6: Retención (% que no cancelará <90 días) | B6: 0.9 | D6: Primera mitad (50%) | E6: =E5/2 -> 0
D7: Segunda mitad (50%) | E7: =E5/2 -> 0
A9: PROYECCIÓN DE INGRESOS
A10: Periodo | B10: Ventas | C10: Comisión bruta | D10: Efectiva (tras retención) | E10: Acumulado
A11: 1 mes | B11: =$B$5*1 -> 10 | C11: =B11*$E$5 -> 0 | D11: =C11*$B$6 -> 0 | E11: =D11 -> 0
A12: 3 meses | B12: =$B$5*3 -> 30 | C12: =B12*$E$5 -> 0 | D12: =C12*$B$6 -> 0 | E12: =D12 -> 0
A13: 6 meses | B13: =$B$5*6 -> 60 | C13: =B13*$E$5 -> 0 | D13: =C13*$B$6 -> 0 | E13: =D13 -> 0
A14: 12 meses (1 año) | B14: =$B$5*12 -> 120 | C14: =B14*$E$5 -> 0 | D14: =C14*$B$6 -> 0 | E14: =D14 -> 0
A15: 24 meses (2 años) | B15: =$B$5*24 -> 240 | C15: =B15*$E$5 -> 0 | D15: =C15*$B$6 -> 0 | E15: =D15 -> 0
A18: EJEMPLOS CONCRETOS
A20: ✓ Si vendes 5 Básico al mes → 60 × $448.50 = $26,910/año
A21: ✓ Si vendes 1 Pro al mes → 12 × $898.50 = $10,782/año
A22: ✓ Si vendes 5 Pro al mes → 60 × $898.50 = $53,910/año
A23: ✓ Si vendes 10 Pro al mes → 120 × $898.50 = $107,820/año
A24: ✓ Si vendes 3 Pro + 1 Clínica al mes → (3×$898.50 + 1×$1,798.50) × 12 = $54,126/año
A25: ✓ Si vendes 5 Clínica al mes → 60 × $1,798.50 = $107,910/año 🚀
A26: ✓ Mix realista (5 Básico + 3 Pro + 1 Clínica/mes) → ($2,242.50 + $2,695.50 + $1,798.50) × 12 = $80,838/año
A27: ✓ Nota: solo el plan Free ($0) NO paga comisión. Todos los planes de pago califican.

Sheet Tracking
A1: TRACKING DE VENTAS Y COMISIONES — Captura tus ventas aquí
A2: Llena las columnas amarillas. El Excel calcula automáticamente las comisiones por cobrar, las pagadas y las totales.
A4: # | B4: Fecha venta | C4: Clínica / Doctor | D4: Plan | E4: Comisión total | F4: 1er pago recibido | G4: 2do pago recibido | H4: ¿Cancelada? | I4: Días hasta cancelación | J4: Estado comisión
A5: 1 | E5: =IFERROR(IF(OR(D5="Básico",D5=""),0,VLOOKUP(D5,Planes!A4:C6,3,FALSE)),0) -> 0 | I5: =IF(AND(H5<>"",B5<>""),H5-B5,"") | J5: =IF(C5="","",IF(D5="Básico","No califica",IF(AND(H5<>"",I5<90),"CLAWBACK",IF(AND(F5<>"",G5<>""),"Completa (100%)",IF(F5<>"","1ra mitad (50%)","Pendiente")))))
A6: 2 | E6: =IFERROR(IF(OR(D6="Básico",D6=""),0,VLOOKUP(D6,Planes!A4:C6,3,FALSE)),0) -> 0 | I6: =IF(AND(H6<>"",B6<>""),H6-B6,"") | J6: =IF(C6="","",IF(D6="Básico","No califica",IF(AND(H6<>"",I6<90),"CLAWBACK",IF(AND(F6<>"",G6<>""),"Completa (100%)",IF(F6<>"","1ra mitad (50%)","Pendiente")))))
A7: 3 | E7: =IFERROR(IF(OR(D7="Básico",D7=""),0,VLOOKUP(D7,Planes!A4:C6,3,FALSE)),0) -> 0 | I7: =IF(AND(H7<>"",B7<>""),H7-B7,"") | J7: =IF(C7="","",IF(D7="Básico","No califica",IF(AND(H7<>"",I7<90),"CLAWBACK",IF(AND(F7<>"",G7<>""),"Completa (100%)",IF(F7<>"","1ra mitad (50%)","Pendiente")))))
A8: 4 | E8: =IFERROR(IF(OR(D8="Básico",D8=""),0,VLOOKUP(D8,Planes!A4:C6,3,FALSE)),0) -> 0 | I8: =IF(AND(H8<>"",B8<>""),H8-B8,"") | J8: =IF(C8="","",IF(D8="Básico","No califica",IF(AND(H8<>"",I8<90),"CLAWBACK",IF(AND(F8<>"",G8<>""),"Completa (100%)",IF(F8<>"","1ra mitad (50%)","Pendiente")))))
A9: 5 | E9: =IFERROR(IF(OR(D9="Básico",D9=""),0,VLOOKUP(D9,Planes!A4:C6,3,FALSE)),0) -> 0 | I9: =IF(AND(H9<>"",B9<>""),H9-B9,"") | J9: =IF(C9="","",IF(D9="Básico","No califica",IF(AND(H9<>"",I9<90),"CLAWBACK",IF(AND(F9<>"",G9<>""),"Completa (100%)",IF(F9<>"","1ra mitad (50%)","Pendiente")))))
A10: 6 | E10: =IFERROR(IF(OR(D10="Básico",D10=""),0,VLOOKUP(D10,Planes!A4:C6,3,FALSE)),0) -> 0 | I10: =IF(AND(H10<>"",B10<>""),H10-B10,"") | J10: =IF(C10="","",IF(D10="Básico","No califica",IF(AND(H10<>"",I10<90),"CLAWBACK",IF(AND(F10<>"",G10<>""),"Completa (100%)",IF(F10<>"","1ra mitad (50%)","Pendiente")))))
A11: 7 | E11: =IFERROR(IF(OR(D11="Básico",D11=""),0,VLOOKUP(D11,Planes!A4:C6,3,FALSE)),0) -> 0 | I11: =IF(AND(H11<>"",B11<>""),H11-B11,"") | J11: =IF(C11="","",IF(D11="Básico","No califica",IF(AND(H11<>"",I11<90),"CLAWBACK",IF(AND(F11<>"",G11<>""),"Completa (100%)",IF(F11<>"","1ra mitad (50%)","Pendiente")))))
A12: 8 | E12: =IFERROR(IF(OR(D12="Básico",D12=""),0,VLOOKUP(D12,Planes!A4:C6,3,FALSE)),0) -> 0 | I12: =IF(AND(H12<>"",B12<>""),H12-B12,"") | J12: =IF(C12="","",IF(D12="Básico","No califica",IF(AND(H12<>"",I12<90),"CLAWBACK",IF(AND(F12<>"",G12<>""),"Completa (100%)",IF(F12<>"","1ra mitad (50%)","Pendiente")))))
A13: 9 | E13: =IFERROR(IF(OR(D13="Básico",D13=""),0,VLOOKUP(D13,Planes!A4:C6,3,FALSE)),0) -> 0 | I13: =IF(AND(H13<>"",B13<>""),H13-B13,"") | J13: =IF(C13="","",IF(D13="Básico","No califica",IF(AND(H13<>"",I13<90),"CLAWBACK",IF(AND(F13<>"",G13<>""),"Completa (100%)",IF(F13<>"","1ra mitad (50%)","Pendiente")))))
A14: 10 | E14: =IFERROR(IF(OR(D14="Básico",D14=""),0,VLOOKUP(D14,Planes!A4:C6,3,FALSE)),0) -> 0 | I14: =IF(AND(H14<>"",B14<>""),H14-B14,"") | J14: =IF(C14="","",IF(D14="Básico","No califica",IF(AND(H14<>"",I14<90),"CLAWBACK",IF(AND(F14<>"",G14<>""),"Completa (100%)",IF(F14<>"","1ra mitad (50%)","Pendiente")))))
A15: 11 | E15: =IFERROR(IF(OR(D15="Básico",D15=""),0,VLOOKUP(D15,Planes!A4:C6,3,FALSE)),0) -> 0 | I15: =IF(AND(H15<>"",B15<>""),H15-B15,"") | J15: =IF(C15="","",IF(D15="Básico","No califica",IF(AND(H15<>"",I15<90),"CLAWBACK",IF(AND(F15<>"",G15<>""),"Completa (100%)",IF(F15<>"","1ra mitad (50%)","Pendiente")))))
A16: 12 | E16: =IFERROR(IF(OR(D16="Básico",D16=""),0,VLOOKUP(D16,Planes!A4:C6,3,FALSE)),0) -> 0 | I16: =IF(AND(H16<>"",B16<>""),H16-B16,"") | J16: =IF(C16="","",IF(D16="Básico","No califica",IF(AND(H16<>"",I16<90),"CLAWBACK",IF(AND(F16<>"",G16<>""),"Completa (100%)",IF(F16<>"","1ra mitad (50%)","Pendiente")))))
A17: 13 | E17: =IFERROR(IF(OR(D17="Básico",D17=""),0,VLOOKUP(D17,Planes!A4:C6,3,FALSE)),0) -> 0 | I17: =IF(AND(H17<>"",B17<>""),H17-B17,"") | J17: =IF(C17="","",IF(D17="Básico","No califica",IF(AND(H17<>"",I17<90),"CLAWBACK",IF(AND(F17<>"",G17<>""),"Completa (100%)",IF(F17<>"","1ra mitad (50%)","Pendiente")))))
A18: 14 | E18: =IFERROR(IF(OR(D18="Básico",D18=""),0,VLOOKUP(D18,Planes!A4:C6,3,FALSE)),0) -> 0 | I18: =IF(AND(H18<>"",B18<>""),H18-B18,"") | J18: =IF(C18="","",IF(D18="Básico","No califica",IF(AND(H18<>"",I18<90),"CLAWBACK",IF(AND(F18<>"",G18<>""),"Completa (100%)",IF(F18<>"","1ra mitad (50%)","Pendiente")))))
A19: 15 | E19: =IFERROR(IF(OR(D19="Básico",D19=""),0,VLOOKUP(D19,Planes!A4:C6,3,FALSE)),0) -> 0 | I19: =IF(AND(H19<>"",B19<>""),H19-B19,"") | J19: =IF(C19="","",IF(D19="Básico","No califica",IF(AND(H19<>"",I19<90),"CLAWBACK",IF(AND(F19<>"",G19<>""),"Completa (100%)",IF(F19<>"","1ra mitad (50%)","Pendiente")))))
A20: 16 | E20: =IFERROR(IF(OR(D20="Básico",D20=""),0,VLOOKUP(D20,Planes!A4:C6,3,FALSE)),0) -> 0 | I20: =IF(AND(H20<>"",B20<>""),H20-B20,"") | J20: =IF(C20="","",IF(D20="Básico","No califica",IF(AND(H20<>"",I20<90),"CLAWBACK",IF(AND(F20<>"",G20<>""),"Completa (100%)",IF(F20<>"","1ra mitad (50%)","Pendiente")))))
A21: 17 | E21: =IFERROR(IF(OR(D21="Básico",D21=""),0,VLOOKUP(D21,Planes!A4:C6,3,FALSE)),0) -> 0 | I21: =IF(AND(H21<>"",B21<>""),H21-B21,"") | J21: =IF(C21="","",IF(D21="Básico","No califica",IF(AND(H21<>"",I21<90),"CLAWBACK",IF(AND(F21<>"",G21<>""),"Completa (100%)",IF(F21<>"","1ra mitad (50%)","Pendiente")))))
A22: 18 | E22: =IFERROR(IF(OR(D22="Básico",D22=""),0,VLOOKUP(D22,Planes!A4:C6,3,FALSE)),0) -> 0 | I22: =IF(AND(H22<>"",B22<>""),H22-B22,"") | J22: =IF(C22="","",IF(D22="Básico","No califica",IF(AND(H22<>"",I22<90),"CLAWBACK",IF(AND(F22<>"",G22<>""),"Completa (100%)",IF(F22<>"","1ra mitad (50%)","Pendiente")))))
A23: 19 | E23: =IFERROR(IF(OR(D23="Básico",D23=""),0,VLOOKUP(D23,Planes!A4:C6,3,FALSE)),0) -> 0 | I23: =IF(AND(H23<>"",B23<>""),H23-B23,"") | J23: =IF(C23="","",IF(D23="Básico","No califica",IF(AND(H23<>"",I23<90),"CLAWBACK",IF(AND(F23<>"",G23<>""),"Completa (100%)",IF(F23<>"","1ra mitad (50%)","Pendiente")))))
A24: 20 | E24: =IFERROR(IF(OR(D24="Básico",D24=""),0,VLOOKUP(D24,Planes!A4:C6,3,FALSE)),0) -> 0 | I24: =IF(AND(H24<>"",B24<>""),H24-B24,"") | J24: =IF(C24="","",IF(D24="Básico","No califica",IF(AND(H24<>"",I24<90),"CLAWBACK",IF(AND(F24<>"",G24<>""),"Completa (100%)",IF(F24<>"","1ra mitad (50%)","Pendiente")))))
A25: 21 | E25: =IFERROR(IF(OR(D25="Básico",D25=""),0,VLOOKUP(D25,Planes!A4:C6,3,FALSE)),0) -> 0 | I25: =IF(AND(H25<>"",B25<>""),H25-B25,"") | J25: =IF(C25="","",IF(D25="Básico","No califica",IF(AND(H25<>"",I25<90),"CLAWBACK",IF(AND(F25<>"",G25<>""),"Completa (100%)",IF(F25<>"","1ra mitad (50%)","Pendiente")))))
A26: 22 | E26: =IFERROR(IF(OR(D26="Básico",D26=""),0,VLOOKUP(D26,Planes!A4:C6,3,FALSE)),0) -> 0 | I26: =IF(AND(H26<>"",B26<>""),H26-B26,"") | J26: =IF(C26="","",IF(D26="Básico","No califica",IF(AND(H26<>"",I26<90),"CLAWBACK",IF(AND(F26<>"",G26<>""),"Completa (100%)",IF(F26<>"","1ra mitad (50%)","Pendiente")))))
A27: 23 | E27: =IFERROR(IF(OR(D27="Básico",D27=""),0,VLOOKUP(D27,Planes!A4:C6,3,FALSE)),0) -> 0 | I27: =IF(AND(H27<>"",B27<>""),H27-B27,"") | J27: =IF(C27="","",IF(D27="Básico","No califica",IF(AND(H27<>"",I27<90),"CLAWBACK",IF(AND(F27<>"",G27<>""),"Completa (100%)",IF(F27<>"","1ra mitad (50%)","Pendiente")))))
A28: 24 | E28: =IFERROR(IF(OR(D28="Básico",D28=""),0,VLOOKUP(D28,Planes!A4:C6,3,FALSE)),0) -> 0 | I28: =IF(AND(H28<>"",B28<>""),H28-B28,"") | J28: =IF(C28="","",IF(D28="Básico","No califica",IF(AND(H28<>"",I28<90),"CLAWBACK",IF(AND(F28<>"",G28<>""),"Completa (100%)",IF(F28<>"","1ra mitad (50%)","Pendiente")))))
A29: 25 | E29: =IFERROR(IF(OR(D29="Básico",D29=""),0,VLOOKUP(D29,Planes!A4:C6,3,FALSE)),0) -> 0 | I29: =IF(AND(H29<>"",B29<>""),H29-B29,"") | J29: =IF(C29="","",IF(D29="Básico","No califica",IF(AND(H29<>"",I29<90),"CLAWBACK",IF(AND(F29<>"",G29<>""),"Completa (100%)",IF(F29<>"","1ra mitad (50%)","Pendiente")))))
A30: 26 | E30: =IFERROR(IF(OR(D30="Básico",D30=""),0,VLOOKUP(D30,Planes!A4:C6,3,FALSE)),0) -> 0 | I30: =IF(AND(H30<>"",B30<>""),H30-B30,"") | J30: =IF(C30="","",IF(D30="Básico","No califica",IF(AND(H30<>"",I30<90),"CLAWBACK",IF(AND(F30<>"",G30<>""),"Completa (100%)",IF(F30<>"","1ra mitad (50%)","Pendiente")))))
A31: 27 | E31: =IFERROR(IF(OR(D31="Básico",D31=""),0,VLOOKUP(D31,Planes!A4:C6,3,FALSE)),0) -> 0 | I31: =IF(AND(H31<>"",B31<>""),H31-B31,"") | J31: =IF(C31="","",IF(D31="Básico","No califica",IF(AND(H31<>"",I31<90),"CLAWBACK",IF(AND(F31<>"",G31<>""),"Completa (100%)",IF(F31<>"","1ra mitad (50%)","Pendiente")))))
A32: 28 | E32: =IFERROR(IF(OR(D32="Básico",D32=""),0,VLOOKUP(D32,Planes!A4:C6,3,FALSE)),0) -> 0 | I32: =IF(AND(H32<>"",B32<>""),H32-B32,"") | J32: =IF(C32="","",IF(D32="Básico","No califica",IF(AND(H32<>"",I32<90),"CLAWBACK",IF(AND(F32<>"",G32<>""),"Completa (100%)",IF(F32<>"","1ra mitad (50%)","Pendiente")))))
A33: 29 | E33: =IFERROR(IF(OR(D33="Básico",D33=""),0,VLOOKUP(D33,Planes!A4:C6,3,FALSE)),0) -> 0 | I33: =IF(AND(H33<>"",B33<>""),H33-B33,"") | J33: =IF(C33="","",IF(D33="Básico","No califica",IF(AND(H33<>"",I33<90),"CLAWBACK",IF(AND(F33<>"",G33<>""),"Completa (100%)",IF(F33<>"","1ra mitad (50%)","Pendiente")))))
A34: 30 | E34: =IFERROR(IF(OR(D34="Básico",D34=""),0,VLOOKUP(D34,Planes!A4:C6,3,FALSE)),0) -> 0 | I34: =IF(AND(H34<>"",B34<>""),H34-B34,"") | J34: =IF(C34="","",IF(D34="Básico","No califica",IF(AND(H34<>"",I34<90),"CLAWBACK",IF(AND(F34<>"",G34<>""),"Completa (100%)",IF(F34<>"","1ra mitad (50%)","Pendiente")))))
A36: RESUMEN
A37: Ventas capturadas: | E37: =COUNTA(C5:C34) -> 0
A38: Comisión generada (sin clawback): | E38: =SUMIFS(E5:E34,J5:J34,"Completa*")+SUMIFS(E5:E34,J5:J34,"1ra mitad*")/2 -> 0
A39: Comisión pendiente de cobrar: | E39: =SUMIFS(E5:E34,J5:J34,"Pendiente*") -> 0
A40: Comisión en clawback (a descontar): | E40: =SUMIFS(E5:E34,J5:J34,"CLAWBACK") -> 0

Sheet Planes
A1: TABLA DE PLANES — Usada por las fórmulas
A3: Plan | B3: Precio mensual | C3: Comisión total (1.5×) | D3: Por mitad (50%) | E3: ¿Califica?
A4: Free | B4: 0 | C4: 0 | D4: 0 | E4: NO
A5: Básico | B5: 149 | C5: 223.5 | D5: 111.75 | E5: SÍ
A6: Pro | B6: 299 | C6: 448.5 | D6: 224.25 | E6: SÍ
A7: Clínica | B7: 499 | C7: 748.5 | D7: 374.25 | E7: SÍ
A9: NOTA: Todos los planes de pago (Básico, Pro, Clínica) pagan comisión. Solo el plan Free NO paga.
A10: La comisión es 1.5× la mensualidad, dividida en 2 pagos (al 1er y al 2do pago del cliente).
