Workbook

Sheet Resumen
A1: DocFácil — Corridas de caja del módulo de ventas
A2: Parámetros: 3 vendedores × 10 ventas/mes · comisión 3× split 50/50 · churn 2.5% mensual
A4: Plan | B4: Precio mensual | C4: Caja mínima | D4: Caja recomendada (+50% colchón) | E4: Breakeven | F4: Margen mensual mes 12
A5: Básico | B5: =Básico!B4 -> 299 | C5: =Básico!F28 -> 20847.407 | D5: =Básico!F29 -> 31271.111 | E5: Mes 6 | F5: =Básico!F31 -> 55549.781
A6: Profesional | B6: =Profesional!B4 -> 599 | C6: =Profesional!F28 -> 38295.356 | D6: =Profesional!F29 -> 57443.034 | E6: Mes 6 | F6: =Profesional!F31 -> 117446.94
A7: Clínica | B7: =Clínica!B4 -> 1199 | C7: =Clínica!F28 -> 71465.32 | D7: =Clínica!F29 -> 107197.98 | E7: Mes 6 | F7: =Clínica!F31 -> 244306.68
A9: NOTAS IMPORTANTES
A10: 1. Supuestos: sin rampa de vendedores (cierran 10/mes desde el mes 1). En realidad es menos el primer mes.
A11: 2. Costo operativo: Básico $20/cliente/mes, Profesional $30, Clínica $50 (incluye hosting, WhatsApp, email, Stripe fees).
A12: 3. Mes 3 es siempre el peor momento: pagas la segunda mitad del cohorte 2 + la primera del cohorte 3.
A13: 4. Breakeven cae en mes 6 en los 3 escenarios por la estructura 50/50.
A14: 5. Si el vendedor cierra solo 5/mes en lugar de 10, multiplica todo por 0.5 (caja mínima y breakeven).
A15: 6. Las comisiones se pagan SOLO si el cliente hace su primer pago (50%) y su segundo pago (50%). Si cancela antes de 90 días, clawback.
A16: 7. Cada hoja tiene parámetros editables arriba. Cambia # vendedores, churn, precio, ventas/mes y todo se recalcula.
A17: 8. MRR = Monthly Recurring Revenue = ingreso recurrente mensual por clientes activos.

Sheet Básico
A1: PARÁMETROS EDITABLES — cambia los valores y toda la tabla se recalcula
A3: Plan | B3: Básico | D3: Valores derivados
A4: Precio mensual (MXN) | B4: 299 | D4: Nuevos/mes | E4: =B5*B6 -> 30
A5: # Vendedores | B5: 3 | D5: Comisión total/venta | E5: =B4*B7 -> 897
A6: Ventas/mes por vendedor | B6: 10 | D6: Primera mitad/venta | E6: =E5*B8 -> 448.5
A7: Multiplicador comisión | B7: 3 | D7: Segunda mitad/venta | E7: =E5*(1-B8) -> 448.5
A8: Split primera mitad (%) | B8: 0.5
A9: Churn mensual (%) | B9: 0.025
A10: Costo operativo/cliente (MXN) | B10: 30
A13: Mes | B13: Activos inicio | C13: Nuevos | D13: Activos después churn | E13: Ingreso MRR | F13: Costo operativo | G13: Comisión mes 1ra | H13: Comisión mes 2da | I13: Comisión total | J13: Neto mes | K13: Acumulado
A14: 1 | B14: 0 | C14: =$E$4 -> 30 | D14: =(B14+C14)*(1-$B$9) -> 29.25 | E14: =D14*$B$4 -> 8745.75 | F14: =-D14*$B$10 -> -877.5 | G14: =-C14*$E$6 -> -13455 | H14: 0 | I14: =G14+H14 -> -13455 | J14: =E14+F14+I14 -> -5586.75 | K14: =J14 -> -5586.75
A15: 2 | B15: =D14 -> 29.25 | C15: =$E$4 -> 30 | D15: =(B15+C15)*(1-$B$9) -> 57.76875 | E15: =D15*$B$4 -> 17272.856 | F15: =-D15*$B$10 -> -1733.0625 | G15: =-C15*$E$6 -> -13455 | H15: =-C14*$E$7 -> -13455 | I15: =G15+H15 -> -26910 | J15: =E15+F15+I15 -> -11370.206 | K15: =K14+J15 -> -16956.956
A16: 3 | B16: =D15 -> 57.76875 | C16: =$E$4 -> 30 | D16: =(B16+C16)*(1-$B$9) -> 85.574531 | E16: =D16*$B$4 -> 25586.785 | F16: =-D16*$B$10 -> -2567.2359 | G16: =-C16*$E$6 -> -13455 | H16: =-C15*$E$7 -> -13455 | I16: =G16+H16 -> -26910 | J16: =E16+F16+I16 -> -3890.4511 | K16: =K15+J16 -> -20847.407
A17: 4 | B17: =D16 -> 85.574531 | C17: =$E$4 -> 30 | D17: =(B17+C17)*(1-$B$9) -> 112.68517 | E17: =D17*$B$4 -> 33692.865 | F17: =-D17*$B$10 -> -3380.555 | G17: =-C17*$E$6 -> -13455 | H17: =-C16*$E$7 -> -13455 | I17: =G17+H17 -> -26910 | J17: =E17+F17+I17 -> 3402.3102 | K17: =K16+J17 -> -17445.097
A18: 5 | B18: =D17 -> 112.68517 | C18: =$E$4 -> 30 | D18: =(B18+C18)*(1-$B$9) -> 139.11804 | E18: =D18*$B$4 -> 41596.294 | F18: =-D18*$B$10 -> -4173.5412 | G18: =-C18*$E$6 -> -13455 | H18: =-C17*$E$7 -> -13455 | I18: =G18+H18 -> -26910 | J18: =E18+F18+I18 -> 10512.752 | K18: =K17+J18 -> -6932.3447
A19: 6 | B19: =D18 -> 139.11804 | C19: =$E$4 -> 30 | D19: =(B19+C19)*(1-$B$9) -> 164.89009 | E19: =D19*$B$4 -> 49302.136 | F19: =-D19*$B$10 -> -4946.7026 | G19: =-C19*$E$6 -> -13455 | H19: =-C18*$E$7 -> -13455 | I19: =G19+H19 -> -26910 | J19: =E19+F19+I19 -> 17445.434 | K19: =K18+J19 -> 10513.089
A20: 7 | B20: =D19 -> 164.89009 | C20: =$E$4 -> 30 | D20: =(B20+C20)*(1-$B$9) -> 190.01784 | E20: =D20*$B$4 -> 56815.333 | F20: =-D20*$B$10 -> -5700.5351 | G20: =-C20*$E$6 -> -13455 | H20: =-C19*$E$7 -> -13455 | I20: =G20+H20 -> -26910 | J20: =E20+F20+I20 -> 24204.798 | K20: =K19+J20 -> 34717.887
A21: 8 | B21: =D20 -> 190.01784 | C21: =$E$4 -> 30 | D21: =(B21+C21)*(1-$B$9) -> 214.51739 | E21: =D21*$B$4 -> 64140.7 | F21: =-D21*$B$10 -> -6435.5217 | G21: =-C21*$E$6 -> -13455 | H21: =-C20*$E$7 -> -13455 | I21: =G21+H21 -> -26910 | J21: =E21+F21+I21 -> 30795.178 | K21: =K20+J21 -> 65513.064
A22: 9 | B22: =D21 -> 214.51739 | C22: =$E$4 -> 30 | D22: =(B22+C22)*(1-$B$9) -> 238.40445 | E22: =D22*$B$4 -> 71282.932 | F22: =-D22*$B$10 -> -7152.1336 | G22: =-C22*$E$6 -> -13455 | H22: =-C21*$E$7 -> -13455 | I22: =G22+H22 -> -26910 | J22: =E22+F22+I22 -> 37220.798 | K22: =K21+J22 -> 102733.86
A23: 10 | B23: =D22 -> 238.40445 | C23: =$E$4 -> 30 | D23: =(B23+C23)*(1-$B$9) -> 261.69434 | E23: =D23*$B$4 -> 78246.609 | F23: =-D23*$B$10 -> -7850.8303 | G23: =-C23*$E$6 -> -13455 | H23: =-C22*$E$7 -> -13455 | I23: =G23+H23 -> -26910 | J23: =E23+F23+I23 -> 43485.778 | K23: =K22+J23 -> 146219.64
A24: 11 | B24: =D23 -> 261.69434 | C24: =$E$4 -> 30 | D24: =(B24+C24)*(1-$B$9) -> 284.40199 | E24: =D24*$B$4 -> 85036.194 | F24: =-D24*$B$10 -> -8532.0596 | G24: =-C24*$E$6 -> -13455 | H24: =-C23*$E$7 -> -13455 | I24: =G24+H24 -> -26910 | J24: =E24+F24+I24 -> 49594.134 | K24: =K23+J24 -> 195813.78
A25: 12 | B25: =D24 -> 284.40199 | C25: =$E$4 -> 30 | D25: =(B25+C25)*(1-$B$9) -> 306.54194 | E25: =D25*$B$4 -> 91656.039 | F25: =-D25*$B$10 -> -9196.2581 | G25: =-C25*$E$6 -> -13455 | H25: =-C24*$E$7 -> -13455 | I25: =G25+H25 -> -26910 | J25: =E25+F25+I25 -> 55549.781 | K25: =K24+J25 -> 251363.56
A27: INDICADORES CLAVE
A28: Caja mínima requerida (el valor más negativo del acumulado) | F28: =ABS(MIN(K14:K25)) -> 20847.407
A29: Caja recomendada (mínima + 50% colchón) | F29: =F28*1.5 -> 31271.111
A30: Ingreso mensual mes 12 (MRR estimado) | F30: =E25 -> 91656.039
A31: Margen neto mensual mes 12 | F31: =J25 -> 55549.781

Sheet Profesional
A1: PARÁMETROS EDITABLES — cambia los valores y toda la tabla se recalcula
A3: Plan | B3: Pro | D3: Valores derivados
A4: Precio mensual (MXN) | B4: 599 | D4: Nuevos/mes | E4: =B5*B6 -> 30
A5: # Vendedores | B5: 3 | D5: Comisión total/venta | E5: =B4*B7 -> 1797
A6: Ventas/mes por vendedor | B6: 10 | D6: Primera mitad/venta | E6: =E5*B8 -> 898.5
A7: Multiplicador comisión | B7: 3 | D7: Segunda mitad/venta | E7: =E5*(1-B8) -> 898.5
A8: Split primera mitad (%) | B8: 0.5
A9: Churn mensual (%) | B9: 0.025
A10: Costo operativo/cliente (MXN) | B10: 40
A13: Mes | B13: Activos inicio | C13: Nuevos | D13: Activos después churn | E13: Ingreso MRR | F13: Costo operativo | G13: Comisión mes 1ra | H13: Comisión mes 2da | I13: Comisión total | J13: Neto mes | K13: Acumulado
A14: 1 | B14: 0 | C14: =$E$4 -> 30 | D14: =(B14+C14)*(1-$B$9) -> 29.25 | E14: =D14*$B$4 -> 17520.75 | F14: =-D14*$B$10 -> -1170 | G14: =-C14*$E$6 -> -26955 | H14: 0 | I14: =G14+H14 -> -26955 | J14: =E14+F14+I14 -> -10604.25 | K14: =J14 -> -10604.25
A15: 2 | B15: =D14 -> 29.25 | C15: =$E$4 -> 30 | D15: =(B15+C15)*(1-$B$9) -> 57.76875 | E15: =D15*$B$4 -> 34603.481 | F15: =-D15*$B$10 -> -2310.75 | G15: =-C15*$E$6 -> -26955 | H15: =-C14*$E$7 -> -26955 | I15: =G15+H15 -> -53910 | J15: =E15+F15+I15 -> -21617.269 | K15: =K14+J15 -> -32221.519
A16: 3 | B16: =D15 -> 57.76875 | C16: =$E$4 -> 30 | D16: =(B16+C16)*(1-$B$9) -> 85.574531 | E16: =D16*$B$4 -> 51259.144 | F16: =-D16*$B$10 -> -3422.9812 | G16: =-C16*$E$6 -> -26955 | H16: =-C15*$E$7 -> -26955 | I16: =G16+H16 -> -53910 | J16: =E16+F16+I16 -> -6073.837 | K16: =K15+J16 -> -38295.356
A17: 4 | B17: =D16 -> 85.574531 | C17: =$E$4 -> 30 | D17: =(B17+C17)*(1-$B$9) -> 112.68517 | E17: =D17*$B$4 -> 67498.416 | F17: =-D17*$B$10 -> -4507.4067 | G17: =-C17*$E$6 -> -26955 | H17: =-C16*$E$7 -> -26955 | I17: =G17+H17 -> -53910 | J17: =E17+F17+I17 -> 9081.0089 | K17: =K16+J17 -> -29214.347
A18: 5 | B18: =D17 -> 112.68517 | C18: =$E$4 -> 30 | D18: =(B18+C18)*(1-$B$9) -> 139.11804 | E18: =D18*$B$4 -> 83331.705 | F18: =-D18*$B$10 -> -5564.7216 | G18: =-C18*$E$6 -> -26955 | H18: =-C17*$E$7 -> -26955 | I18: =G18+H18 -> -53910 | J18: =E18+F18+I18 -> 23856.984 | K18: =K17+J18 -> -5357.3632
A19: 6 | B19: =D18 -> 139.11804 | C19: =$E$4 -> 30 | D19: =(B19+C19)*(1-$B$9) -> 164.89009 | E19: =D19*$B$4 -> 98769.163 | F19: =-D19*$B$10 -> -6595.6035 | G19: =-C19*$E$6 -> -26955 | H19: =-C18*$E$7 -> -26955 | I19: =G19+H19 -> -53910 | J19: =E19+F19+I19 -> 38263.559 | K19: =K18+J19 -> 32906.196
A20: 7 | B20: =D19 -> 164.89009 | C20: =$E$4 -> 30 | D20: =(B20+C20)*(1-$B$9) -> 190.01784 | E20: =D20*$B$4 -> 113820.68 | F20: =-D20*$B$10 -> -7600.7134 | G20: =-C20*$E$6 -> -26955 | H20: =-C19*$E$7 -> -26955 | I20: =G20+H20 -> -53910 | J20: =E20+F20+I20 -> 52309.97 | K20: =K19+J20 -> 85216.166
A21: 8 | B21: =D20 -> 190.01784 | C21: =$E$4 -> 30 | D21: =(B21+C21)*(1-$B$9) -> 214.51739 | E21: =D21*$B$4 -> 128495.92 | F21: =-D21*$B$10 -> -8580.6956 | G21: =-C21*$E$6 -> -26955 | H21: =-C20*$E$7 -> -26955 | I21: =G21+H21 -> -53910 | J21: =E21+F21+I21 -> 66005.221 | K21: =K20+J21 -> 151221.39
A22: 9 | B22: =D21 -> 214.51739 | C22: =$E$4 -> 30 | D22: =(B22+C22)*(1-$B$9) -> 238.40445 | E22: =D22*$B$4 -> 142804.27 | F22: =-D22*$B$10 -> -9536.1782 | G22: =-C22*$E$6 -> -26955 | H22: =-C21*$E$7 -> -26955 | I22: =G22+H22 -> -53910 | J22: =E22+F22+I22 -> 79358.09 | K22: =K21+J22 -> 230579.48
A23: 10 | B23: =D22 -> 238.40445 | C23: =$E$4 -> 30 | D23: =(B23+C23)*(1-$B$9) -> 261.69434 | E23: =D23*$B$4 -> 156754.91 | F23: =-D23*$B$10 -> -10467.774 | G23: =-C23*$E$6 -> -26955 | H23: =-C22*$E$7 -> -26955 | I23: =G23+H23 -> -53910 | J23: =E23+F23+I23 -> 92377.138 | K23: =K22+J23 -> 322956.62
A24: 11 | B24: =D23 -> 261.69434 | C24: =$E$4 -> 30 | D24: =(B24+C24)*(1-$B$9) -> 284.40199 | E24: =D24*$B$4 -> 170356.79 | F24: =-D24*$B$10 -> -11376.079 | G24: =-C24*$E$6 -> -26955 | H24: =-C23*$E$7 -> -26955 | I24: =G24+H24 -> -53910 | J24: =E24+F24+I24 -> 105070.71 | K24: =K23+J24 -> 428027.32
A25: 12 | B25: =D24 -> 284.40199 | C25: =$E$4 -> 30 | D25: =(B25+C25)*(1-$B$9) -> 306.54194 | E25: =D25*$B$4 -> 183618.62 | F25: =-D25*$B$10 -> -12261.677 | G25: =-C25*$E$6 -> -26955 | H25: =-C24*$E$7 -> -26955 | I25: =G25+H25 -> -53910 | J25: =E25+F25+I25 -> 117446.94 | K25: =K24+J25 -> 545474.27
A27: INDICADORES CLAVE
A28: Caja mínima requerida (el valor más negativo del acumulado) | F28: =ABS(MIN(K14:K25)) -> 38295.356
A29: Caja recomendada (mínima + 50% colchón) | F29: =F28*1.5 -> 57443.034
A30: Ingreso mensual mes 12 (MRR estimado) | F30: =E25 -> 183618.62
A31: Margen neto mensual mes 12 | F31: =J25 -> 117446.94

Sheet Clínica
A1: PARÁMETROS EDITABLES — cambia los valores y toda la tabla se recalcula
A3: Plan | B3: Clínica | D3: Valores derivados
A4: Precio mensual (MXN) | B4: 1199 | D4: Nuevos/mes | E4: =B5*B6 -> 30
A5: # Vendedores | B5: 3 | D5: Comisión total/venta | E5: =B4*B7 -> 3597
A6: Ventas/mes por vendedor | B6: 10 | D6: Primera mitad/venta | E6: =E5*B8 -> 1798.5
A7: Multiplicador comisión | B7: 3 | D7: Segunda mitad/venta | E7: =E5*(1-B8) -> 1798.5
A8: Split primera mitad (%) | B8: 0.5
A9: Churn mensual (%) | B9: 0.025
A10: Costo operativo/cliente (MXN) | B10: 50
A13: Mes | B13: Activos inicio | C13: Nuevos | D13: Activos después churn | E13: Ingreso MRR | F13: Costo operativo | G13: Comisión mes 1ra | H13: Comisión mes 2da | I13: Comisión total | J13: Neto mes | K13: Acumulado
A14: 1 | B14: 0 | C14: =$E$4 -> 30 | D14: =(B14+C14)*(1-$B$9) -> 29.25 | E14: =D14*$B$4 -> 35070.75 | F14: =-D14*$B$10 -> -1462.5 | G14: =-C14*$E$6 -> -53955 | H14: 0 | I14: =G14+H14 -> -53955 | J14: =E14+F14+I14 -> -20346.75 | K14: =J14 -> -20346.75
A15: 2 | B15: =D14 -> 29.25 | C15: =$E$4 -> 30 | D15: =(B15+C15)*(1-$B$9) -> 57.76875 | E15: =D15*$B$4 -> 69264.731 | F15: =-D15*$B$10 -> -2888.4375 | G15: =-C15*$E$6 -> -53955 | H15: =-C14*$E$7 -> -53955 | I15: =G15+H15 -> -107910 | J15: =E15+F15+I15 -> -41533.706 | K15: =K14+J15 -> -61880.456
A16: 3 | B16: =D15 -> 57.76875 | C16: =$E$4 -> 30 | D16: =(B16+C16)*(1-$B$9) -> 85.574531 | E16: =D16*$B$4 -> 102603.86 | F16: =-D16*$B$10 -> -4278.7266 | G16: =-C16*$E$6 -> -53955 | H16: =-C15*$E$7 -> -53955 | I16: =G16+H16 -> -107910 | J16: =E16+F16+I16 -> -9584.8636 | K16: =K15+J16 -> -71465.32
A17: 4 | B17: =D16 -> 85.574531 | C17: =$E$4 -> 30 | D17: =(B17+C17)*(1-$B$9) -> 112.68517 | E17: =D17*$B$4 -> 135109.52 | F17: =-D17*$B$10 -> -5634.2584 | G17: =-C17*$E$6 -> -53955 | H17: =-C16*$E$7 -> -53955 | I17: =G17+H17 -> -107910 | J17: =E17+F17+I17 -> 21565.258 | K17: =K16+J17 -> -49900.062
A18: 5 | B18: =D17 -> 112.68517 | C18: =$E$4 -> 30 | D18: =(B18+C18)*(1-$B$9) -> 139.11804 | E18: =D18*$B$4 -> 166802.53 | F18: =-D18*$B$10 -> -6955.9019 | G18: =-C18*$E$6 -> -53955 | H18: =-C17*$E$7 -> -53955 | I18: =G18+H18 -> -107910 | J18: =E18+F18+I18 -> 51936.627 | K18: =K17+J18 -> 2036.5647
A19: 6 | B19: =D18 -> 139.11804 | C19: =$E$4 -> 30 | D19: =(B19+C19)*(1-$B$9) -> 164.89009 | E19: =D19*$B$4 -> 197703.22 | F19: =-D19*$B$10 -> -8244.5044 | G19: =-C19*$E$6 -> -53955 | H19: =-C18*$E$7 -> -53955 | I19: =G19+H19 -> -107910 | J19: =E19+F19+I19 -> 81548.711 | K19: =K18+J19 -> 83585.276
A20: 7 | B20: =D19 -> 164.89009 | C20: =$E$4 -> 30 | D20: =(B20+C20)*(1-$B$9) -> 190.01784 | E20: =D20*$B$4 -> 227831.38 | F20: =-D20*$B$10 -> -9500.8918 | G20: =-C20*$E$6 -> -53955 | H20: =-C19*$E$7 -> -53955 | I20: =G20+H20 -> -107910 | J20: =E20+F20+I20 -> 110420.49 | K20: =K19+J20 -> 194005.77
A21: 8 | B21: =D20 -> 190.01784 | C21: =$E$4 -> 30 | D21: =(B21+C21)*(1-$B$9) -> 214.51739 | E21: =D21*$B$4 -> 257206.35 | F21: =-D21*$B$10 -> -10725.869 | G21: =-C21*$E$6 -> -53955 | H21: =-C20*$E$7 -> -53955 | I21: =G21+H21 -> -107910 | J21: =E21+F21+I21 -> 138570.48 | K21: =K20+J21 -> 332576.25
A22: 9 | B22: =D21 -> 214.51739 | C22: =$E$4 -> 30 | D22: =(B22+C22)*(1-$B$9) -> 238.40445 | E22: =D22*$B$4 -> 285846.94 | F22: =-D22*$B$10 -> -11920.223 | G22: =-C22*$E$6 -> -53955 | H22: =-C21*$E$7 -> -53955 | I22: =G22+H22 -> -107910 | J22: =E22+F22+I22 -> 166016.72 | K22: =K21+J22 -> 498592.97
A23: 10 | B23: =D22 -> 238.40445 | C23: =$E$4 -> 30 | D23: =(B23+C23)*(1-$B$9) -> 261.69434 | E23: =D23*$B$4 -> 313771.52 | F23: =-D23*$B$10 -> -13084.717 | G23: =-C23*$E$6 -> -53955 | H23: =-C22*$E$7 -> -53955 | I23: =G23+H23 -> -107910 | J23: =E23+F23+I23 -> 192776.8 | K23: =K22+J23 -> 691369.77
A24: 11 | B24: =D23 -> 261.69434 | C24: =$E$4 -> 30 | D24: =(B24+C24)*(1-$B$9) -> 284.40199 | E24: =D24*$B$4 -> 340997.98 | F24: =-D24*$B$10 -> -14220.099 | G24: =-C24*$E$6 -> -53955 | H24: =-C23*$E$7 -> -53955 | I24: =G24+H24 -> -107910 | J24: =E24+F24+I24 -> 218867.88 | K24: =K23+J24 -> 910237.65
A25: 12 | B25: =D24 -> 284.40199 | C25: =$E$4 -> 30 | D25: =(B25+C25)*(1-$B$9) -> 306.54194 | E25: =D25*$B$4 -> 367543.78 | F25: =-D25*$B$10 -> -15327.097 | G25: =-C25*$E$6 -> -53955 | H25: =-C24*$E$7 -> -53955 | I25: =G25+H25 -> -107910 | J25: =E25+F25+I25 -> 244306.68 | K25: =K24+J25 -> 1154544.3
A27: INDICADORES CLAVE
A28: Caja mínima requerida (el valor más negativo del acumulado) | F28: =ABS(MIN(K14:K25)) -> 71465.32
A29: Caja recomendada (mínima + 50% colchón) | F29: =F28*1.5 -> 107197.98
A30: Ingreso mensual mes 12 (MRR estimado) | F30: =E25 -> 367543.78
A31: Margen neto mensual mes 12 | F31: =J25 -> 244306.68
